mongopie/__init__.py
mongopie/cli.py
mongopie/mongopie.py
mongopie-0.1.0.dev1.dist-info/AUTHORS.rst
mongopie-0.1.0.dev1.dist-info/LICENSE
mongopie-0.1.0.dev1.dist-info/METADATA
mongopie-0.1.0.dev1.dist-info/WHEEL
mongopie-0.1.0.dev1.dist-info/entry_points.txt
mongopie-0.1.0.dev1.dist-info/top_level.txt
mongopie-0.1.0.dev1.dist-info/RECORD
