Metadata-Version: 2.1
Name: mongopie
Version: 0.1.0.dev1
Summary: Simple MongoDB ODM
Home-page: https://github.com/Windfarer/mongopie
Author: Windfarer
Author-email: windfarer@gmail.com
License: Apache Software License 2.0
Keywords: mongopie
Platform: UNKNOWN
Classifier: Development Status :: 2 - Pre-Alpha
Classifier: Intended Audience :: Developers
Classifier: License :: OSI Approved :: Apache Software License
Classifier: Natural Language :: English
Classifier: Programming Language :: Python :: 2
Classifier: Programming Language :: Python :: 2.7
Classifier: Programming Language :: Python :: 3
Classifier: Programming Language :: Python :: 3.5
Classifier: Programming Language :: Python :: 3.6
Classifier: Programming Language :: Python :: 3.7
Requires-Python: >=2.7, !=3.0.*, !=3.1.*, !=3.2.*, !=3.3.*, !=3.4.*
Requires-Dist: Click (>=7.0)
